setup.py
dlx/__init__.py
dlx.egg-info/PKG-INFO
dlx.egg-info/SOURCES.txt
dlx.egg-info/dependency_links.txt
dlx.egg-info/top_level.txt