Metadata-Version: 1.0
Name: dlx
Version: 1.0.2
Summary: Implementation of Donald Knuth's Dancing Links algorithm.
Home-page: http://www.site.uottawa.ca/~mraap046
Author: Sebastian Raaphorst
Author-email: srcoding@gmail.com
License: GPL
Keywords: exact cover algorithm dlx dancing links
Platform: UNKNOWN
Classifier: License :: OSI Approved :: Apache Software License
Classifier: Programming Language :: Python
Classifier: Development Status :: 4 - Beta
Classifier: Intended Audience :: Developers
Classifier: Topic :: Scientific/Engineering :: Mathematics
